[
  {
    "Id": 11,
    "CreatedBy": 124,
    "CreatedOn": "2019-09-02 08:18:35.813",
    "IsActive": "1",
    "IsCatastropheRegion": "0",
    "IsDeleted": "0",
    "Name": "Georgia",
    "RegionLead": 11299
  },
  {
    "Id": 12,
    "CreatedBy": 43444,
    "CreatedOn": "2019-09-09 15:18:01.193",
    "IsActive": "1",
    "IsCatastropheRegion": "0",
    "IsDeleted": "0",
    "Name": "Carolinas",
    "RegionLead": 227
  },
  {
    "Id": 13,
    "CreatedBy": 124,
    "CreatedOn": "2019-09-02 08:19:22.987",
    "IsActive": "1",
    "IsCatastropheRegion": "0",
    "IsDeleted": "0",
    "Name": "Delta",
    "RegionLead": null
  },
  {
    "Id": 14,
    "CreatedBy": 124,
    "CreatedOn": "2019-09-01 17:15:29.587",
    "IsActive": "1",
    "IsCatastropheRegion": "0",
    "IsDeleted": "0",
    "Name": "Mid-Atlantic",
    "RegionLead": 10789
  },
  {
    "Id": 15,
    "CreatedBy": 124,
    "CreatedOn": "2019-09-01 17:19:44.320",
    "IsActive": "1",
    "IsCatastropheRegion": "0",
    "IsDeleted": "0",
    "Name": "Ohio Valley",
    "RegionLead": 13550
  },
  {
    "Id": 16,
    "CreatedBy": 124,
    "CreatedOn": "2019-09-01 17:18:15.643",
    "IsActive": "1",
    "IsCatastropheRegion": "0",
    "IsDeleted": "0",
    "Name": "Great Lakes",
    "RegionLead": 6754
  },
  {
    "Id": 17,
    "CreatedBy": 124,
    "CreatedOn": "2019-09-01 17:03:26.653",
    "IsActive": "1",
    "IsCatastropheRegion": "0",
    "IsDeleted": "0",
    "Name": "Southwest",
    "RegionLead": 11804
  },
  {
    "Id": 18,
    "CreatedBy": 124,
    "CreatedOn": "2019-09-01 17:15:01.647",
    "IsActive": "1",
    "IsCatastropheRegion": "0",
    "IsDeleted": "0",
    "Name": "Rockies",
    "RegionLead": 14179
  },
  {
    "Id": 19,
    "CreatedBy": 124,
    "CreatedOn": "2019-09-01 17:15:47.497",
    "IsActive": "1",
    "IsCatastropheRegion": "0",
    "IsDeleted": "0",
    "Name": "Northeast",
    "RegionLead": 7198
  },
  {
    "Id": 22,
    "CreatedBy": 41217,
    "CreatedOn": "2019-06-17 17:12:57.107",
    "IsActive": "1",
    "IsCatastropheRegion": "0",
    "IsDeleted": "0",
    "Name": "Training",
    "RegionLead": 4020
  },
  {
    "Id": 24,
    "CreatedBy": 124,
    "CreatedOn": "2019-09-01 17:09:10.333",
    "IsActive": "1",
    "IsCatastropheRegion": "0",
    "IsDeleted": "0",
    "Name": "New England",
    "RegionLead": 146
  },
  {
    "Id": 26,
    "CreatedBy": 22874,
    "CreatedOn": "2019-08-21 14:14:18.163",
    "IsActive": "1",
    "IsCatastropheRegion": "0",
    "IsDeleted": "0",
    "Name": "CAT",
    "RegionLead": null
  },
  {
    "Id": 27,
    "CreatedBy": 3332,
    "CreatedOn": "2019-09-09 11:48:59.233",
    "IsActive": "1",
    "IsCatastropheRegion": "0",
    "IsDeleted": "0",
    "Name": "Midwest",
    "RegionLead": 10035
  },
  {
    "Id": 28,
    "CreatedBy": 124,
    "CreatedOn": "2019-09-02 08:19:37.627",
    "IsActive": "1",
    "IsCatastropheRegion": "0",
    "IsDeleted": "0",
    "Name": "TN Valley",
    "RegionLead": 3854
  },
  {
    "Id": 30,
    "CreatedBy": 22874,
    "CreatedOn": "2019-09-06 15:08:38.463",
    "IsActive": "1",
    "IsCatastropheRegion": "0",
    "IsDeleted": "0",
    "Name": "Central",
    "RegionLead": 30289
  },
  {
    "Id": 32,
    "CreatedBy": 32996,
    "CreatedOn": "2018-08-05 14:00:46.977",
    "IsActive": "1",
    "IsCatastropheRegion": "0",
    "IsDeleted": "0",
    "Name": "******",
    "RegionLead": null
  },
  {
    "Id": 33,
    "CreatedBy": 31661,
    "CreatedOn": "2019-03-03 10:56:27.110",
    "IsActive": "1",
    "IsCatastropheRegion": "0",
    "IsDeleted": "0",
    "Name": "*",
    "RegionLead": null
  },
  {
    "Id": 34,
    "CreatedBy": 124,
    "CreatedOn": "2019-09-02 08:18:21.487",
    "IsActive": "1",
    "IsCatastropheRegion": "0",
    "IsDeleted": "0",
    "Name": "Florida",
    "RegionLead": 18713
  },
  {
    "Id": 35,
    "CreatedBy": 124,
    "CreatedOn": "2019-09-01 17:14:39.463",
    "IsActive": "1",
    "IsCatastropheRegion": "0",
    "IsDeleted": "0",
    "Name": "Great Plains",
    "RegionLead": 35522
  }
]
